inventree_wled_locator/WledPlugin.py
inventree_wled_locator/__init__.py
inventree_wled_locator-0.4.0.dist-info/LICENSE
inventree_wled_locator-0.4.0.dist-info/METADATA
inventree_wled_locator-0.4.0.dist-info/WHEEL
inventree_wled_locator-0.4.0.dist-info/entry_points.txt
inventree_wled_locator-0.4.0.dist-info/top_level.txt
inventree_wled_locator-0.4.0.dist-info/RECORD
