Metadata-Version: 2.1
Name: inventree-wled-locator
Version: 0.4.0
Summary: Use WLED to locate InvenTree StockLocations.
Author-email: Matthias Mair <code@mjmair.com>
License: MIT license
Project-URL: Repository, https://github.com/invenhost/inventree-wled-locator
Project-URL: Bug Tracker, https://github.com/invenhost/inventree-wled-locator/issues
Keywords: inventree,inventree-plugin,inventree-wled-locator
Classifier: Programming Language :: Python :: 3
Classifier: Operating System :: OS Independent
Classifier: Development Status :: 5 - Production/Stable
Classifier: Environment :: Plugins
Classifier: Framework :: Django
Classifier: Intended Audience :: Developers
Classifier: Intended Audience :: Manufacturing
Classifier: Intended Audience :: End Users/Desktop
Classifier: Topic :: Scientific/Engineering
Classifier: License :: OSI Approved :: MIT License
Requires-Python: >=3.9
License-File: LICENSE
Requires-Dist: django
Requires-Dist: requests
Provides-Extra: dev
Requires-Dist: twine ; extra == 'dev'
Requires-Dist: setuptools ; extra == 'dev'
